{
  "version": [
    1,
    0
  ],
  "type": "Eco.Gameplay.Civics.Laws.Law",
  "name": "Tax Framework",
  "reference": false,
  "description": null,
  "properties": {
    "Sections": [
      {
        "type": "Eco.Gameplay.Civics.Laws.LawSection",
        "reference": false,
        "properties": {
          "Title": "Tax Collection every 3 Hours",
          "UserDescription": "every three hours, taxes are collected from every citizen.",
          "Triggers": [
            {
              "type": "Eco.Gameplay.Civics.Laws.TriggerSettings",
              "reference": false,
              "properties": {
                "Trigger": {
                  "type": "Type",
                  "value": "Eco.Gameplay.GameActions.CitizenTimer"
                },
                "Configs": [
                  {
                    "type": "Eco.Gameplay.GameActions.CitizenTimerTriggerConfig",
                    "typeToConfig": null,
                    "propNameBacker": null,
                    "propDisplayName": null,
                    "properties": {
                      "RepeatForEachUser": {
                        "type": "Eco.Gameplay.Civics.Demographics.Demographic",
                        "name": "Everyone",
                        "reference": true
                      },
                      "HoursBetweenExecutions": 3.0
                    }
                  }
                ]
              }
            }
          ],
          "IfThenBlocks": [
            {
              "type": "Eco.Gameplay.Civics.IfThenBlock",
              "reference": false,
              "properties": {
                "If": {
                  "type": "Eco.Gameplay.Civics.GameValues.SetOfConditions",
                  "properties": {
                    "List": [
                      {
                        "type": "Eco.Gameplay.Civics.GameValues.Compare",
                        "properties": {
                          "Left": {
                            "type": "Eco.Gameplay.Civics.GameValues.CustomStatQuery",
                            "properties": {
                              "CustomStatName": "taxesOwed",
                              "TimeRangeInHours": {
                                "type": "GameValueWrapper",
                                "value": 0.0
                              },
                              "TimeRangeType": "CountBackFromPresentTime",
                              "User": {
                                "type": "GameValueContext",
                                "contextName": "Citizen",
                                "titleBacking": "<ecoicon item=\"User\">Citizen</ecoicon>",
                                "tooltip": "When triggered, the <ecoicon item=\"User\">Citizen</ecoicon> value of the event will be used.\r\n\r\n<ecoicon item=\"User\">Citizen</ecoicon>: The citizen currently being processed for the timer event.\r\n"
                              }
                            }
                          },
                          "Comparison": "GreaterThan",
                          "Right": {
                            "type": "GameValueWrapper",
                            "value": 0.0
                          }
                        }
                      },
                      {
                        "type": "Eco.Gameplay.Civics.GameValues.Compare",
                        "properties": {
                          "Left": {
                            "type": "Eco.Gameplay.Civics.GameValues.Values.Wealth",
                            "properties": {
                              "Currency": {
                                "type": "GameValueWrapper",
                                "value": {
                                  "type": "Eco.Gameplay.Economy.Currency",
                                  "name": "Dollar",
                                  "reference": true
                                }
                              },
                              "Citizen": {
                                "type": "GameValueContext",
                                "contextName": "Citizen",
                                "titleBacking": "<ecoicon item=\"User\">Citizen</ecoicon>",
                                "tooltip": "When triggered, the <ecoicon item=\"User\">Citizen</ecoicon> value of the event will be used.\r\n\r\n<ecoicon item=\"User\">Citizen</ecoicon>: The citizen currently being processed for the timer event.\r\n"
                              }
                            }
                          },
                          "Comparison": "GreaterThan",
                          "Right": {
                            "type": "Eco.Gameplay.Civics.GameValues.CustomStatQuery",
                            "properties": {
                              "CustomStatName": "taxesOwed",
                              "TimeRangeInHours": {
                                "type": "GameValueWrapper",
                                "value": 0.0
                              },
                              "TimeRangeType": "CountBackFromPresentTime",
                              "User": {
                                "type": "GameValueContext",
                                "contextName": "Citizen",
                                "titleBacking": "<ecoicon item=\"User\">Citizen</ecoicon>",
                                "tooltip": "When triggered, the <ecoicon item=\"User\">Citizen</ecoicon> value of the event will be used.\r\n\r\n<ecoicon item=\"User\">Citizen</ecoicon>: The citizen currently being processed for the timer event.\r\n"
                              }
                            }
                          }
                        }
                      }
                    ],
                    "Comparison": "All"
                  }
                },
                "Then": [
                  {
                    "type": "Eco.Gameplay.Civics.Tax_LegalAction",
                    "reference": false,
                    "properties": {
                      "TargetBankAccount": {
                        "type": "GameValueWrapper",
                        "value": {
                          "type": "Eco.Gameplay.Economy.TreasuryBankAccount",
                          "name": "Treasury Bank Account",
                          "reference": true
                        }
                      },
                      "Target": {
                        "type": "GameValueContext",
                        "contextName": "Citizen",
                        "titleBacking": "<ecoicon item=\"User\">Citizen</ecoicon>",
                        "tooltip": "When triggered, the <ecoicon item=\"User\">Citizen</ecoicon> value of the event will be used.\r\n\r\n<ecoicon item=\"User\">Citizen</ecoicon>: The citizen currently being processed for the timer event.\r\n"
                      },
                      "Currency": {
                        "type": "GameValueWrapper",
                        "value": {
                          "type": "Eco.Gameplay.Economy.Currency",
                          "name": "Dollar",
                          "reference": true
                        }
                      },
                      "Amount": {
                        "type": "Eco.Gameplay.Civics.GameValues.CustomStatQuery",
                        "properties": {
                          "CustomStatName": "taxesOwed",
                          "TimeRangeInHours": {
                            "type": "GameValueWrapper",
                            "value": 0.0
                          },
                          "TimeRangeType": "CountBackFromPresentTime",
                          "User": {
                            "type": "GameValueContext",
                            "contextName": "Citizen",
                            "titleBacking": "<ecoicon item=\"User\">Citizen</ecoicon>",
                            "tooltip": "When triggered, the <ecoicon item=\"User\">Citizen</ecoicon> value of the event will be used.\r\n\r\n<ecoicon item=\"User\">Citizen</ecoicon>: The citizen currently being processed for the timer event.\r\n"
                          }
                        }
                      },
                      "PreventIfUnableToPay": {
                        "type": "Eco.Gameplay.Civics.GameValues.No",
                        "properties": {}
                      },
                      "InfoboxOnSuccess": {
                        "type": "Eco.Gameplay.Civics.GameValues.No",
                        "properties": {}
                      }
                    }
                  },
                  {
                    "type": "Eco.Gameplay.Civics.GameValues.RecordCustomStat",
                    "reference": false,
                    "properties": {
                      "StatName": "taxesPaid",
                      "Person": {
                        "type": "GameValueContext",
                        "contextName": "Citizen",
                        "titleBacking": "<ecoicon item=\"User\">Citizen</ecoicon>",
                        "tooltip": "When triggered, the <ecoicon item=\"User\">Citizen</ecoicon> value of the event will be used.\r\n\r\n<ecoicon item=\"User\">Citizen</ecoicon>: The citizen currently being processed for the timer event.\r\n"
                      },
                      "Count": {
                        "type": "Eco.Gameplay.Civics.GameValues.CustomStatQuery",
                        "properties": {
                          "CustomStatName": "taxesOwed",
                          "TimeRangeInHours": {
                            "type": "GameValueWrapper",
                            "value": 0.0
                          },
                          "TimeRangeType": "CountBackFromPresentTime",
                          "User": {
                            "type": "GameValueContext",
                            "contextName": "Citizen",
                            "titleBacking": "<ecoicon item=\"User\">Citizen</ecoicon>",
                            "tooltip": "When triggered, the <ecoicon item=\"User\">Citizen</ecoicon> value of the event will be used.\r\n\r\n<ecoicon item=\"User\">Citizen</ecoicon>: The citizen currently being processed for the timer event.\r\n"
                          }
                        }
                      },
                      "InfoboxOnSuccess": {
                        "type": "Eco.Gameplay.Civics.GameValues.No",
                        "properties": {}
                      }
                    }
                  },
                  {
                    "type": "Eco.Gameplay.Civics.GameValues.RecordCustomStat",
                    "reference": false,
                    "properties": {
                      "StatName": "taxesOwed",
                      "Person": {
                        "type": "GameValueContext",
                        "contextName": "Citizen",
                        "titleBacking": "<ecoicon item=\"User\">Citizen</ecoicon>",
                        "tooltip": "When triggered, the <ecoicon item=\"User\">Citizen</ecoicon> value of the event will be used.\r\n\r\n<ecoicon item=\"User\">Citizen</ecoicon>: The citizen currently being processed for the timer event.\r\n"
                      },
                      "Count": {
                        "type": "Eco.Gameplay.Civics.GameValues.Arithmetic",
                        "properties": {
                          "LeftNumber": {
                            "type": "GameValueWrapper",
                            "value": -1.0
                          },
                          "Operation": "Multiply",
                          "RightNumber": {
                            "type": "Eco.Gameplay.Civics.GameValues.CustomStatQuery",
                            "properties": {
                              "CustomStatName": "taxesOwed",
                              "TimeRangeInHours": {
                                "type": "GameValueWrapper",
                                "value": 0.0
                              },
                              "TimeRangeType": "CountBackFromPresentTime",
                              "User": {
                                "type": "GameValueContext",
                                "contextName": "Citizen",
                                "titleBacking": "<ecoicon item=\"User\">Citizen</ecoicon>",
                                "tooltip": "When triggered, the <ecoicon item=\"User\">Citizen</ecoicon> value of the event will be used.\r\n\r\n<ecoicon item=\"User\">Citizen</ecoicon>: The citizen currently being processed for the timer event.\r\n"
                              }
                            }
                          }
                        }
                      },
                      "InfoboxOnSuccess": {
                        "type": "Eco.Gameplay.Civics.GameValues.No",
                        "properties": {}
                      }
                    }
                  }
                ]
              }
            },
            {
              "type": "Eco.Gameplay.Civics.IfThenBlock",
              "reference": false,
              "properties": {
                "If": {
                  "type": "Eco.Gameplay.Civics.GameValues.SetOfConditions",
                  "properties": {
                    "List": [
                      {
                        "type": "Eco.Gameplay.Civics.GameValues.Compare",
                        "properties": {
                          "Left": {
                            "type": "Eco.Gameplay.Civics.GameValues.CustomStatQuery",
                            "properties": {
                              "CustomStatName": "taxesOwed",
                              "TimeRangeInHours": {
                                "type": "GameValueWrapper",
                                "value": 0.0
                              },
                              "TimeRangeType": "CountBackFromPresentTime",
                              "User": {
                                "type": "GameValueContext",
                                "contextName": "Citizen",
                                "titleBacking": "<ecoicon item=\"User\">Citizen</ecoicon>",
                                "tooltip": "When triggered, the <ecoicon item=\"User\">Citizen</ecoicon> value of the event will be used.\r\n\r\n<ecoicon item=\"User\">Citizen</ecoicon>: The citizen currently being processed for the timer event.\r\n"
                              }
                            }
                          },
                          "Comparison": "GreaterThan",
                          "Right": {
                            "type": "GameValueWrapper",
                            "value": 0.0
                          }
                        }
                      }
                    ],
                    "Comparison": "All"
                  }
                },
                "Then": [
                  {
                    "type": "Eco.Gameplay.Civics.GameValues.RecordCustomStat",
                    "reference": false,
                    "properties": {
                      "StatName": "taxesOwed",
                      "Person": {
                        "type": "GameValueContext",
                        "contextName": "Citizen",
                        "titleBacking": "<ecoicon item=\"User\">Citizen</ecoicon>",
                        "tooltip": "When triggered, the <ecoicon item=\"User\">Citizen</ecoicon> value of the event will be used.\r\n\r\n<ecoicon item=\"User\">Citizen</ecoicon>: The citizen currently being processed for the timer event.\r\n"
                      },
                      "Count": {
                        "type": "Eco.Gameplay.Civics.GameValues.Arithmetic",
                        "properties": {
                          "LeftNumber": {
                            "type": "GameValueWrapper",
                            "value": -1.0
                          },
                          "Operation": "Multiply",
                          "RightNumber": {
                            "type": "Eco.Gameplay.Civics.GameValues.Values.Wealth",
                            "properties": {
                              "Currency": {
                                "type": "GameValueWrapper",
                                "value": {
                                  "type": "Eco.Gameplay.Economy.Currency",
                                  "name": "Dollar",
                                  "reference": true
                                }
                              },
                              "Citizen": {
                                "type": "GameValueContext",
                                "contextName": "Citizen",
                                "titleBacking": "<ecoicon item=\"User\">Citizen</ecoicon>",
                                "tooltip": "When triggered, the <ecoicon item=\"User\">Citizen</ecoicon> value of the event will be used.\r\n\r\n<ecoicon item=\"User\">Citizen</ecoicon>: The citizen currently being processed for the timer event.\r\n"
                              }
                            }
                          }
                        }
                      },
                      "InfoboxOnSuccess": {
                        "type": "Eco.Gameplay.Civics.GameValues.No",
                        "properties": {}
                      }
                    }
                  },
                  {
                    "type": "Eco.Gameplay.Civics.GameValues.RecordCustomStat",
                    "reference": false,
                    "properties": {
                      "StatName": "taxesPaid",
                      "Person": {
                        "type": "GameValueContext",
                        "contextName": "Citizen",
                        "titleBacking": "<ecoicon item=\"User\">Citizen</ecoicon>",
                        "tooltip": "When triggered, the <ecoicon item=\"User\">Citizen</ecoicon> value of the event will be used.\r\n\r\n<ecoicon item=\"User\">Citizen</ecoicon>: The citizen currently being processed for the timer event.\r\n"
                      },
                      "Count": {
                        "type": "Eco.Gameplay.Civics.GameValues.Values.Wealth",
                        "properties": {
                          "Currency": {
                            "type": "GameValueWrapper",
                            "value": {
                              "type": "Eco.Gameplay.Economy.Currency",
                              "name": "Dollar",
                              "reference": true
                            }
                          },
                          "Citizen": {
                            "type": "GameValueContext",
                            "contextName": "Citizen",
                            "titleBacking": "<ecoicon item=\"User\">Citizen</ecoicon>",
                            "tooltip": "When triggered, the <ecoicon item=\"User\">Citizen</ecoicon> value of the event will be used.\r\n\r\n<ecoicon item=\"User\">Citizen</ecoicon>: The citizen currently being processed for the timer event.\r\n"
                          }
                        }
                      },
                      "InfoboxOnSuccess": {
                        "type": "Eco.Gameplay.Civics.GameValues.No",
                        "properties": {}
                      }
                    }
                  },
                  {
                    "type": "Eco.Gameplay.Civics.Tax_LegalAction",
                    "reference": false,
                    "properties": {
                      "TargetBankAccount": {
                        "type": "GameValueWrapper",
                        "value": {
                          "type": "Eco.Gameplay.Economy.TreasuryBankAccount",
                          "name": "Treasury Bank Account",
                          "reference": true
                        }
                      },
                      "Target": {
                        "type": "GameValueContext",
                        "contextName": "Citizen",
                        "titleBacking": "<ecoicon item=\"User\">Citizen</ecoicon>",
                        "tooltip": "When triggered, the <ecoicon item=\"User\">Citizen</ecoicon> value of the event will be used.\r\n\r\n<ecoicon item=\"User\">Citizen</ecoicon>: The citizen currently being processed for the timer event.\r\n"
                      },
                      "Currency": {
                        "type": "GameValueWrapper",
                        "value": {
                          "type": "Eco.Gameplay.Economy.Currency",
                          "name": "Dollar",
                          "reference": true
                        }
                      },
                      "Amount": {
                        "type": "Eco.Gameplay.Civics.GameValues.Values.Wealth",
                        "properties": {
                          "Currency": {
                            "type": "GameValueWrapper",
                            "value": {
                              "type": "Eco.Gameplay.Economy.Currency",
                              "name": "Dollar",
                              "reference": true
                            }
                          },
                          "Citizen": {
                            "type": "GameValueContext",
                            "contextName": "Citizen",
                            "titleBacking": "<ecoicon item=\"User\">Citizen</ecoicon>",
                            "tooltip": "When triggered, the <ecoicon item=\"User\">Citizen</ecoicon> value of the event will be used.\r\n\r\n<ecoicon item=\"User\">Citizen</ecoicon>: The citizen currently being processed for the timer event.\r\n"
                          }
                        }
                      },
                      "PreventIfUnableToPay": {
                        "type": "Eco.Gameplay.Civics.GameValues.No",
                        "properties": {}
                      },
                      "InfoboxOnSuccess": {
                        "type": "Eco.Gameplay.Civics.GameValues.No",
                        "properties": {}
                      }
                    }
                  }
                ]
              }
            }
          ]
        }
      },
      {
        "type": "Eco.Gameplay.Civics.Laws.LawSection",
        "reference": false,
        "properties": {
          "Title": "Taxes Owed Query",
          "UserDescription": "",
          "Triggers": [
            {
              "type": "Eco.Gameplay.Civics.Laws.TriggerSettings",
              "reference": false,
              "properties": {
                "Trigger": {
                  "type": "Type",
                  "value": "Eco.Gameplay.GameActions.ChatSent"
                },
                "Configs": [
                  {
                    "type": "Eco.Gameplay.GameActions.SelectString",
                    "typeToConfig": "Eco.Gameplay.GameActions.ChatSent",
                    "propNameBacker": "Tag",
                    "propDisplayName": "Tag",
                    "properties": {
                      "String": null
                    }
                  },
                  {
                    "type": "Eco.Gameplay.GameActions.SelectString",
                    "typeToConfig": "Eco.Gameplay.GameActions.ChatSent",
                    "propNameBacker": "Message",
                    "propDisplayName": "Message",
                    "properties": {
                      "String": "!taxes"
                    }
                  }
                ]
              }
            }
          ],
          "IfThenBlocks": [
            {
              "type": "Eco.Gameplay.Civics.IfThenBlock",
              "reference": false,
              "properties": {
                "If": {
                  "type": "Eco.Gameplay.Civics.GameValues.SetOfConditions",
                  "properties": {
                    "List": [],
                    "Comparison": "All"
                  }
                },
                "Then": [
                  {
                    "type": "Eco.Gameplay.Civics.SendNotice",
                    "reference": false,
                    "properties": {
                      "Message": "you owe a total of:",
                      "NotificationType": "SideBarMessage",
                      "PeopleToSendTo": {
                        "type": "GameValueContext",
                        "contextName": "Citizen",
                        "titleBacking": "<ecoicon item=\"User\">Citizen</ecoicon>",
                        "tooltip": "When triggered, the <ecoicon item=\"User\">Citizen</ecoicon> value of the event will be used.\r\n\r\n<ecoicon item=\"User\">Citizen</ecoicon>: The citizen who performed the interaction.\r\n"
                      },
                      "ValueToDisplay": {
                        "type": "Eco.Gameplay.Civics.GameValues.CustomStatQuery",
                        "properties": {
                          "CustomStatName": "taxesOwed",
                          "TimeRangeInHours": {
                            "type": "GameValueWrapper",
                            "value": 0.0
                          },
                          "TimeRangeType": "CountBackFromPresentTime",
                          "User": {
                            "type": "GameValueContext",
                            "contextName": "Citizen",
                            "titleBacking": "<ecoicon item=\"User\">Citizen</ecoicon>",
                            "tooltip": "When triggered, the <ecoicon item=\"User\">Citizen</ecoicon> value of the event will be used.\r\n\r\n<ecoicon item=\"User\">Citizen</ecoicon>: The citizen who performed the interaction.\r\n"
                          }
                        }
                      },
                      "LocationToDisplay": null,
                      "InfoboxOnSuccess": {
                        "type": "Eco.Gameplay.Civics.GameValues.No",
                        "properties": {}
                      }
                    }
                  }
                ]
              }
            }
          ]
        }
      },
      {
        "type": "Eco.Gameplay.Civics.Laws.LawSection",
        "reference": false,
        "properties": {
          "Title": "Taxes Paid Today Query",
          "UserDescription": "",
          "Triggers": [
            {
              "type": "Eco.Gameplay.Civics.Laws.TriggerSettings",
              "reference": false,
              "properties": {
                "Trigger": {
                  "type": "Type",
                  "value": "Eco.Gameplay.GameActions.ChatSent"
                },
                "Configs": [
                  {
                    "type": "Eco.Gameplay.GameActions.SelectString",
                    "typeToConfig": "Eco.Gameplay.GameActions.ChatSent",
                    "propNameBacker": "Tag",
                    "propDisplayName": "Tag",
                    "properties": {
                      "String": null
                    }
                  },
                  {
                    "type": "Eco.Gameplay.GameActions.SelectString",
                    "typeToConfig": "Eco.Gameplay.GameActions.ChatSent",
                    "propNameBacker": "Message",
                    "propDisplayName": "Message",
                    "properties": {
                      "String": "!taxestoday"
                    }
                  }
                ]
              }
            }
          ],
          "IfThenBlocks": [
            {
              "type": "Eco.Gameplay.Civics.IfThenBlock",
              "reference": false,
              "properties": {
                "If": {
                  "type": "Eco.Gameplay.Civics.GameValues.SetOfConditions",
                  "properties": {
                    "List": [],
                    "Comparison": "All"
                  }
                },
                "Then": [
                  {
                    "type": "Eco.Gameplay.Civics.SendNotice",
                    "reference": false,
                    "properties": {
                      "Message": "taxes paid today:",
                      "NotificationType": "SideBarMessage",
                      "PeopleToSendTo": {
                        "type": "GameValueContext",
                        "contextName": "Citizen",
                        "titleBacking": "<ecoicon item=\"User\">Citizen</ecoicon>",
                        "tooltip": "When triggered, the <ecoicon item=\"User\">Citizen</ecoicon> value of the event will be used.\r\n\r\n<ecoicon item=\"User\">Citizen</ecoicon>: The citizen who performed the interaction.\r\n"
                      },
                      "ValueToDisplay": {
                        "type": "Eco.Gameplay.Civics.GameValues.CustomStatQuery",
                        "properties": {
                          "CustomStatName": "taxesPaid",
                          "TimeRangeInHours": {
                            "type": "GameValueWrapper",
                            "value": 24.0
                          },
                          "TimeRangeType": "CountBackFromPresentTime",
                          "User": {
                            "type": "GameValueContext",
                            "contextName": "Citizen",
                            "titleBacking": "<ecoicon item=\"User\">Citizen</ecoicon>",
                            "tooltip": "When triggered, the <ecoicon item=\"User\">Citizen</ecoicon> value of the event will be used.\r\n\r\n<ecoicon item=\"User\">Citizen</ecoicon>: The citizen who performed the interaction.\r\n"
                          }
                        }
                      },
                      "LocationToDisplay": null,
                      "InfoboxOnSuccess": {
                        "type": "Eco.Gameplay.Civics.GameValues.No",
                        "properties": {}
                      }
                    }
                  }
                ]
              }
            }
          ]
        }
      },
      {
        "type": "Eco.Gameplay.Civics.Laws.LawSection",
        "reference": false,
        "properties": {
          "Title": "Taxes Paid Total Query",
          "UserDescription": "",
          "Triggers": [
            {
              "type": "Eco.Gameplay.Civics.Laws.TriggerSettings",
              "reference": false,
              "properties": {
                "Trigger": {
                  "type": "Type",
                  "value": "Eco.Gameplay.GameActions.ChatSent"
                },
                "Configs": [
                  {
                    "type": "Eco.Gameplay.GameActions.SelectString",
                    "typeToConfig": "Eco.Gameplay.GameActions.ChatSent",
                    "propNameBacker": "Tag",
                    "propDisplayName": "Tag",
                    "properties": {
                      "String": null
                    }
                  },
                  {
                    "type": "Eco.Gameplay.GameActions.SelectString",
                    "typeToConfig": "Eco.Gameplay.GameActions.ChatSent",
                    "propNameBacker": "Message",
                    "propDisplayName": "Message",
                    "properties": {
                      "String": "!taxestotal"
                    }
                  }
                ]
              }
            }
          ],
          "IfThenBlocks": [
            {
              "type": "Eco.Gameplay.Civics.IfThenBlock",
              "reference": false,
              "properties": {
                "If": {
                  "type": "Eco.Gameplay.Civics.GameValues.SetOfConditions",
                  "properties": {
                    "List": [],
                    "Comparison": "All"
                  }
                },
                "Then": [
                  {
                    "type": "Eco.Gameplay.Civics.SendNotice",
                    "reference": false,
                    "properties": {
                      "Message": "total taxes paid:",
                      "NotificationType": "SideBarMessage",
                      "PeopleToSendTo": {
                        "type": "GameValueContext",
                        "contextName": "Citizen",
                        "titleBacking": "<ecoicon item=\"User\">Citizen</ecoicon>",
                        "tooltip": "When triggered, the <ecoicon item=\"User\">Citizen</ecoicon> value of the event will be used.\r\n\r\n<ecoicon item=\"User\">Citizen</ecoicon>: The citizen who performed the interaction.\r\n"
                      },
                      "ValueToDisplay": {
                        "type": "Eco.Gameplay.Civics.GameValues.CustomStatQuery",
                        "properties": {
                          "CustomStatName": "taxesPaid",
                          "TimeRangeInHours": {
                            "type": "GameValueWrapper",
                            "value": 0.0
                          },
                          "TimeRangeType": "CountBackFromPresentTime",
                          "User": {
                            "type": "GameValueContext",
                            "contextName": "Citizen",
                            "titleBacking": "<ecoicon item=\"User\">Citizen</ecoicon>",
                            "tooltip": "When triggered, the <ecoicon item=\"User\">Citizen</ecoicon> value of the event will be used.\r\n\r\n<ecoicon item=\"User\">Citizen</ecoicon>: The citizen who performed the interaction.\r\n"
                          }
                        }
                      },
                      "LocationToDisplay": null,
                      "InfoboxOnSuccess": {
                        "type": "Eco.Gameplay.Civics.GameValues.No",
                        "properties": {}
                      }
                    }
                  }
                ]
              }
            }
          ]
        }
      }
    ]
  }
}